flytekitplugins_pydantic-1.14.9-py3.13-nspkg.pth
flytekitplugins/pydantic/__init__.py
flytekitplugins/pydantic/basemodel_transformer.py
flytekitplugins/pydantic/commons.py
flytekitplugins/pydantic/deserialization.py
flytekitplugins/pydantic/serialization.py
flytekitplugins_pydantic-1.14.9.dist-info/METADATA
flytekitplugins_pydantic-1.14.9.dist-info/WHEEL
flytekitplugins_pydantic-1.14.9.dist-info/entry_points.txt
flytekitplugins_pydantic-1.14.9.dist-info/namespace_packages.txt
flytekitplugins_pydantic-1.14.9.dist-info/top_level.txt
flytekitplugins_pydantic-1.14.9.dist-info/RECORD
